kml_heartbeat
