Metadata-Version: 2.1
Name: kml-sdk
Version: 0.0.6
Summary: KMl_SDK
Home-page: https://github.com/pypa/sampleproject
Author: zhusichuang
Author-email: zhu_sichuang@163.com
License: UNKNOWN
Platform: UNKNOWN
Classifier: Programming Language :: Python :: 2.7
Classifier: License :: OSI Approved :: MIT License
